<?xml version='1.0' encoding='UTF-8'?><factura version='1.1.0' id='comprobante'><infoTributaria><ambiente>2</ambiente><tipoEmision>1</tipoEmision><razonSocial>SOCASI SOCASI MARCO GIOVANNI</razonSocial><nombreComercial>BODEGA EL EJIDO</nombreComercial><ruc>1715168975001</ruc><claveAcceso>1903202301171516897500120010010000012651234567814</claveAcceso><codDoc>01</codDoc><estab>001</estab><ptoEmi>001</ptoEmi><secuencial>000001265</secuencial><dirMatriz>VIA A TAMBILLO LOTE S/N Y PASAJE S/N</dirMatriz></infoTributaria><infoFactura><fechaEmision>19/03/2023</fechaEmision><dirEstablecimiento>VIA A TAMBILLO LOTE S/N Y PASAJE S/N</dirEstablecimiento><obligadoContabilidad>NO</obligadoContabilidad><tipoIdentificacionComprador>07</tipoIdentificacionComprador><razonSocialComprador>CONSUMIDOR FINAL</razonSocialComprador><identificacionComprador>9999999999999</identificacionComprador><totalSinImpuestos>12.32</totalSinImpuestos><totalDescuento>0</totalDescuento><totalConImpuestos><totalImpuesto><codigo>2</codigo><codigoPorcentaje>0</codigoPorcentaje><baseImponible>7</baseImponible><valor>0.00</valor></totalImpuesto><totalImpuesto><codigo>2</codigo><codigoPorcentaje>2</codigoPorcentaje><baseImponible>5.32</baseImponible><valor>0.64</valor></totalImpuesto></totalConImpuestos><propina>0.00</propina><importeTotal>12.96</importeTotal><moneda>DOLAR</moneda><pagos><pago><formaPago>01</formaPago><total>12.96</total></pago></pagos></infoFactura><detalles><detalle><codigoPrincipal>FAM.TIP.1549</codigoPrincipal><codigoAuxiliar>7702133879500</codigoAuxiliar><descripcion>SPARKIES 25GR</descripcion><cantidad>1</cantidad><precioUnitario>0.22</precioUnitario><descuento>0</descuento><precioTotalSinImpuesto>0.22</precioTotalSinImpuesto><impuestos><impuesto><codigo>2</codigo><codigoPorcentaje>2</codigoPorcentaje><tarifa>12</tarifa><baseImponible>0.22</baseImponible><valor>0.03</valor></impuesto></impuestos></detalle><detalle><codigoPrincipal>FAM.TIP.683</codigoPrincipal><codigoAuxiliar>7861048600521</codigoAuxiliar><descripcion>LA SABROSA 1 LIBRA</descripcion><cantidad>1</cantidad><precioUnitario>1</precioUnitario><descuento>0</descuento><precioTotalSinImpuesto>1</precioTotalSinImpuesto><impuestos><impuesto><codigo>2</codigo><codigoPorcentaje>0</codigoPorcentaje><tarifa>0</tarifa><baseImponible>1</baseImponible><valor>0</valor></impuesto></impuestos></detalle><detalle><codigoPrincipal>FAM.TIP.1237</codigoPrincipal><codigoAuxiliar>7861002561042</codigoAuxiliar><descripcion>MANTECA  TRES CHANCH ITOS  1 LIBRA</descripcion><cantidad>1</cantidad><precioUnitario>1.15</precioUnitario><descuento>0</descuento><precioTotalSinImpuesto>1.15</precioTotalSinImpuesto><impuestos><impuesto><codigo>2</codigo><codigoPorcentaje>0</codigoPorcentaje><tarifa>0</tarifa><baseImponible>1.15</baseImponible><valor>0</valor></impuesto></impuestos></detalle><detalle><codigoPrincipal>FAM.TIP.1428</codigoPrincipal><codigoAuxiliar>7862128054135</codigoAuxiliar><descripcion>ACHIOTE CONDIMENSA 190ML</descripcion><cantidad>1</cantidad><precioUnitario>1</precioUnitario><descuento>0</descuento><precioTotalSinImpuesto>1</precioTotalSinImpuesto><impuestos><impuesto><codigo>2</codigo><codigoPorcentaje>0</codigoPorcentaje><tarifa>0</tarifa><baseImponible>1</baseImponible><valor>0</valor></impuesto></impuestos></detalle><detalle><codigoPrincipal>FAM.TIP.1179</codigoPrincipal><codigoAuxiliar>7861065509623</codigoAuxiliar><descripcion>Tatos limon picante 27g</descripcion><cantidad>1</cantidad><precioUnitario>0.22</precioUnitario><descuento>0</descuento><precioTotalSinImpuesto>0.22</precioTotalSinImpuesto><impuestos><impuesto><codigo>2</codigo><codigoPorcentaje>2</codigoPorcentaje><tarifa>12</tarifa><baseImponible>0.22</baseImponible><valor>0.03</valor></impuesto></impuestos></detalle><detalle><codigoPrincipal>FAM.TIP.1396</codigoPrincipal><codigoAuxiliar>7861018590654</codigoAuxiliar><descripcion>CHEETOS MEGA QUESO 46G</descripcion><cantidad>1</cantidad><precioUnitario>0.45</precioUnitario><descuento>0</descuento><precioTotalSinImpuesto>0.45</precioTotalSinImpuesto><impuestos><impuesto><codigo>2</codigo><codigoPorcentaje>2</codigoPorcentaje><tarifa>12</tarifa><baseImponible>0.45</baseImponible><valor>0.05</valor></impuesto></impuestos></detalle><detalle><codigoPrincipal>FAM.TIP.411</codigoPrincipal><codigoAuxiliar>7861048605731</codigoAuxiliar><descripcion>CICLON LIMON 340 GR</descripcion><cantidad>1</cantidad><precioUnitario>0.89</precioUnitario><descuento>0</descuento><precioTotalSinImpuesto>0.89</precioTotalSinImpuesto><impuestos><impuesto><codigo>2</codigo><codigoPorcentaje>2</codigoPorcentaje><tarifa>12</tarifa><baseImponible>0.89</baseImponible><valor>0.11</valor></impuesto></impuestos></detalle><detalle><codigoPrincipal>FAM.TIP.670</codigoPrincipal><codigoAuxiliar>7861002500065</codigoAuxiliar><descripcion>Jabon top combi floral 200 g</descripcion><cantidad>2</cantidad><precioUnitario>0.54</precioUnitario><descuento>0</descuento><precioTotalSinImpuesto>1.08</precioTotalSinImpuesto><impuestos><impuesto><codigo>2</codigo><codigoPorcentaje>2</codigoPorcentaje><tarifa>12</tarifa><baseImponible>1.08</baseImponible><valor>0.13</valor></impuesto></impuestos></detalle><detalle><codigoPrincipal>FAM.TIP.281</codigoPrincipal><codigoAuxiliar>7861002559551</codigoAuxiliar><descripcion>ACEITE COCINERO BOTELLA 900ML</descripcion><cantidad>1</cantidad><precioUnitario>2.85</precioUnitario><descuento>0</descuento><precioTotalSinImpuesto>2.85</precioTotalSinImpuesto><impuestos><impuesto><codigo>2</codigo><codigoPorcentaje>0</codigoPorcentaje><tarifa>0</tarifa><baseImponible>2.85</baseImponible><valor>0</valor></impuesto></impuestos></detalle><detalle><codigoPrincipal>FAM.TIP.099</codigoPrincipal><codigoAuxiliar>7861049300017</codigoAuxiliar><descripcion>Azucar Blanco Valdez 1kg</descripcion><cantidad>1</cantidad><precioUnitario>1</precioUnitario><descuento>0</descuento><precioTotalSinImpuesto>1</precioTotalSinImpuesto><impuestos><impuesto><codigo>2</codigo><codigoPorcentaje>0</codigoPorcentaje><tarifa>0</tarifa><baseImponible>1</baseImponible><valor>0</valor></impuesto></impuestos></detalle><detalle><codigoPrincipal>FAM.TIP.360</codigoPrincipal><codigoAuxiliar>7861018590692</codigoAuxiliar><descripcion>De todito picante 186g</descripcion><cantidad>1</cantidad><precioUnitario>2.01</precioUnitario><descuento>0</descuento><precioTotalSinImpuesto>2.01</precioTotalSinImpuesto><impuestos><impuesto><codigo>2</codigo><codigoPorcentaje>2</codigoPorcentaje><tarifa>12</tarifa><baseImponible>2.01</baseImponible><valor>0.24</valor></impuesto></impuestos></detalle><detalle><codigoPrincipal>FAM.TIP.915</codigoPrincipal><codigoAuxiliar>7862109438268</codigoAuxiliar><descripcion>PEPSI COLA  1LITRO</descripcion><cantidad>1</cantidad><precioUnitario>0.45</precioUnitario><descuento>0</descuento><precioTotalSinImpuesto>0.45</precioTotalSinImpuesto><impuestos><impuesto><codigo>2</codigo><codigoPorcentaje>2</codigoPorcentaje><tarifa>12</tarifa><baseImponible>0.45</baseImponible><valor>0.05</valor></impuesto></impuestos></detalle></detalles><infoAdicional><campoAdicional nombre='Direccion'>AMAGUAÑA</campoAdicional><campoAdicional nombre='Telefono'>09999999</campoAdicional><campoAdicional nombre='Email'>info@hotmail.com</campoAdicional><campoAdicional nombre='Observaciones'> CONTRIBUYENTE REGIMEN RIMPE   </campoAdicional></infoAdicional></factura>