<?xml version='1.0' encoding='UTF-8'?><factura version='1.1.0' id='comprobante'><infoTributaria><ambiente>2</ambiente><tipoEmision>1</tipoEmision><razonSocial>SOCASI SOCASI MARCO GIOVANNI</razonSocial><nombreComercial>BODEGA EL EJIDO</nombreComercial><ruc>1715168975001</ruc><claveAcceso>2202202301171516897500120010010000007961234567819</claveAcceso><codDoc>01</codDoc><estab>001</estab><ptoEmi>001</ptoEmi><secuencial>000000796</secuencial><dirMatriz>VIA A TAMBILLO LOTE S/N Y PASAJE S/N</dirMatriz></infoTributaria><infoFactura><fechaEmision>22/02/2023</fechaEmision><dirEstablecimiento>VIA A TAMBILLO LOTE S/N Y PASAJE S/N</dirEstablecimiento><obligadoContabilidad>NO</obligadoContabilidad><tipoIdentificacionComprador>05</tipoIdentificacionComprador><razonSocialComprador> AMAGUA  QUINGA CARMEN ROCIO</razonSocialComprador><identificacionComprador>1720180833</identificacionComprador><totalSinImpuestos>63.69</totalSinImpuestos><totalDescuento>0</totalDescuento><totalConImpuestos><totalImpuesto><codigo>2</codigo><codigoPorcentaje>0</codigoPorcentaje><baseImponible>4.3</baseImponible><valor>0.00</valor></totalImpuesto><totalImpuesto><codigo>2</codigo><codigoPorcentaje>2</codigoPorcentaje><baseImponible>59.39</baseImponible><valor>7.13</valor></totalImpuesto></totalConImpuestos><propina>0.00</propina><importeTotal>70.82</importeTotal><moneda>DOLAR</moneda><pagos><pago><formaPago>01</formaPago><total>70.82</total></pago></pagos></infoFactura><detalles><detalle><codigoPrincipal>FAM.TIP.281</codigoPrincipal><codigoAuxiliar>7861002559551</codigoAuxiliar><descripcion>ACEITE COCINERO BOTELLA 900ML</descripcion><cantidad>1</cantidad><precioUnitario>2.85</precioUnitario><descuento>0</descuento><precioTotalSinImpuesto>2.85</precioTotalSinImpuesto><impuestos><impuesto><codigo>2</codigo><codigoPorcentaje>0</codigoPorcentaje><tarifa>0</tarifa><baseImponible>2.85</baseImponible><valor>0</valor></impuesto></impuestos></detalle><detalle><codigoPrincipal>FAM.TIP.709</codigoPrincipal><codigoAuxiliar>7861048603881</codigoAuxiliar><descripcion>Lava todo brillex 500 g</descripcion><cantidad>1</cantidad><precioUnitario>1.34</precioUnitario><descuento>0</descuento><precioTotalSinImpuesto>1.34</precioTotalSinImpuesto><impuestos><impuesto><codigo>2</codigo><codigoPorcentaje>2</codigoPorcentaje><tarifa>12</tarifa><baseImponible>1.34</baseImponible><valor>0.16</valor></impuesto></impuestos></detalle><detalle><codigoPrincipal>FAM.TIP.743</codigoPrincipal><descripcion>LONCHYS POLLO 65 GR</descripcion><cantidad>1</cantidad><precioUnitario>0.95</precioUnitario><descuento>0</descuento><precioTotalSinImpuesto>0.95</precioTotalSinImpuesto><impuestos><impuesto><codigo>2</codigo><codigoPorcentaje>0</codigoPorcentaje><tarifa>0</tarifa><baseImponible>0.95</baseImponible><valor>0</valor></impuesto></impuestos></detalle><detalle><codigoPrincipal>FAM.TIP.321</codigoPrincipal><codigoAuxiliar>7622201428815</codigoAuxiliar><descripcion>Coronita galapaguitos 50g</descripcion><cantidad>1</cantidad><precioUnitario>0.45</precioUnitario><descuento>0</descuento><precioTotalSinImpuesto>0.45</precioTotalSinImpuesto><impuestos><impuesto><codigo>2</codigo><codigoPorcentaje>2</codigoPorcentaje><tarifa>12</tarifa><baseImponible>0.45</baseImponible><valor>0.05</valor></impuesto></impuestos></detalle><detalle><codigoPrincipal>FAM.TIP.1354</codigoPrincipal><codigoAuxiliar>7861012512119</codigoAuxiliar><descripcion>YOGURT TONI MIX HOJUELAS 92G</descripcion><cantidad>1</cantidad><precioUnitario>0.5</precioUnitario><descuento>0</descuento><precioTotalSinImpuesto>0.5</precioTotalSinImpuesto><impuestos><impuesto><codigo>2</codigo><codigoPorcentaje>0</codigoPorcentaje><tarifa>0</tarifa><baseImponible>0.5</baseImponible><valor>0</valor></impuesto></impuestos></detalle><detalle><codigoPrincipal>FAM.TIP.175</codigoPrincipal><descripcion>CERVEZA PILSENER DE  1 LITRO JABA X12</descripcion><cantidad>3</cantidad><precioUnitario>19.2</precioUnitario><descuento>0</descuento><precioTotalSinImpuesto>57.6</precioTotalSinImpuesto><impuestos><impuesto><codigo>2</codigo><codigoPorcentaje>2</codigoPorcentaje><tarifa>12</tarifa><baseImponible>57.6</baseImponible><valor>6.91</valor></impuesto></impuestos></detalle></detalles><infoAdicional><campoAdicional nombre='Direccion'>AV. PEDRO VICENTE MALDONADO</campoAdicional><campoAdicional nombre='Telefono'>0988445167</campoAdicional><campoAdicional nombre='Email'>rocioamagua086@gmail.com</campoAdicional><campoAdicional nombre='Observaciones'> CONTRIBUYENTE REGIMEN RIMPE   </campoAdicional></infoAdicional></factura>